taksa/__init__.py
taksa/configuration.py
taksa/dependency.py
taksa/manager.py
taksa/state.py
tests/__init__.py
tests/test_cpp_cmake_dependency.py
taksa_eyelights-0.1.dist-info/LICENSE
taksa_eyelights-0.1.dist-info/METADATA
taksa_eyelights-0.1.dist-info/WHEEL
taksa_eyelights-0.1.dist-info/top_level.txt
taksa_eyelights-0.1.dist-info/RECORD
